pkm_templates/project/render.py
pkm_templates/project/{{project_name}}/README.{{readme_file_ext}}
pkm_templates/project/{{project_name}}/pyproject.toml.tmpl
pkm_templates/project/{{project_name}}/src/{{package_name}}/__init__.py
pkm_templates/project/{{project_name}}/src/{{package_name}}/main.py.tmpl
pkm_templates/envzoo/render.py
pkm_templates/envzoo/{{zoo_name}}/env-zoo.toml.tmpl
pkm_templates/project_from_env/{{environments_toml}}.tmpl
pkm_templates/project_from_env/render.py
pkm_templates/pgroup/render.py
pkm_templates/pgroup/{{group_name}}/pyproject-group.toml.tmpl
pkm_templates/task/render.py
pkm_templates/task/{{task_path}}/{{task_name}}.py
pkm_templates/env/render.py
pkm_cli-0.4.50.dist-info/WHEEL
pkm_cli-0.4.50.dist-info/METADATA
pkm_cli-0.4.50.dist-info/LICENSE
pkm_cli-0.4.50.dist-info/entry_points.txt
pkm_cli/__init__.py
pkm_cli/cli_monitors.py
pkm_cli/main.py
pkm_cli/display/progress.py
pkm_cli/display/__init__.py
pkm_cli/display/display.py
pkm_cli/display/spinner.py
pkm_cli/reports/installed_repositories_report.py
pkm_cli/reports/environment_report.py
pkm_cli/reports/report.py
pkm_cli/reports/project_report.py
pkm_cli/reports/attached_repository_report.py
pkm_cli/reports/pkm_report.py
pkm_cli/reports/__init__.py
pkm_cli/reports/added_repositories_report.py
pkm_cli/reports/package_report.py
pkm_cli/controllers/env_controller.py
pkm_cli/controllers/__init__.py
pkm_cli/controllers/self_controller.py
pkm_cli/controllers/prj_controller.py
pkm_cli/api/__init__.py
pkm_cli/api/templates/__init__.py
pkm_cli/api/templates/template_runner.py
pkm_cli/api/tasks/tasks_runner.py
pkm_cli/api/tasks/__init__.py
pkm_cli/auth/publish_auth_store.py
pkm_cli/auth/__init__.py
pkm_cli/utils/context.py
pkm_cli/utils/__init__.py
pkm_cli/utils/method_clis.py
pkm_cli/utils/clis.py
